practice_japanese/__init__.py
practice_japanese/character_statistics.py
practice_japanese/command_line.py
practice_japanese/version.py
practice_japanese/character_sets/__init__.py
practice_japanese/character_sets/hiragana.py
practice_japanese-0.1.0.dist-info/LICENSE
practice_japanese-0.1.0.dist-info/METADATA
practice_japanese-0.1.0.dist-info/WHEEL
practice_japanese-0.1.0.dist-info/entry_points.txt
practice_japanese-0.1.0.dist-info/top_level.txt
practice_japanese-0.1.0.dist-info/RECORD
