Metadata-Version: 2.1
Name: practice_japanese
Version: 0.1.0
Summary: Practice Japanese character sets.
Home-page: https://github.com/hkeward/practice_japanese
Author: Heather Ward
Author-email: heather.ward13@gmail.com
License: gpl-2.0
Classifier: Programming Language :: Python :: 3
Classifier: License :: OSI Approved :: GNU General Public License v2 (GPLv2)
Classifier: Operating System :: Unix
License-File: LICENSE
